README.md
setup.py
lens_yaml/__init__.py
lens_yaml.egg-info/PKG-INFO
lens_yaml.egg-info/SOURCES.txt
lens_yaml.egg-info/dependency_links.txt
lens_yaml.egg-info/requires.txt
lens_yaml.egg-info/top_level.txt