Metadata-Version: 2.1
Name: lens-yaml
Version: 0.0.1
Summary: A YAML parser for lens
Home-page: https://github.com/port-zero/lens_yaml
Author: Veit Heller
License: MIT
Download-URL: https://github.com/port-zero/lens_yaml/tarball/0.0.1
Platform: UNKNOWN
